demonstrable/whisperx_service/__init__.py
demonstrable/whisperx_service/cli.py
demonstrable/whisperx_service/exceptions.py
demonstrable/whisperx_service/transcription.py
demonstrable_whisperx_service-3.0.0.dist-info/METADATA
demonstrable_whisperx_service-3.0.0.dist-info/WHEEL
demonstrable_whisperx_service-3.0.0.dist-info/entry_points.txt
demonstrable_whisperx_service-3.0.0.dist-info/top_level.txt
demonstrable_whisperx_service-3.0.0.dist-info/RECORD
